decora_bleak/__init__.py
decora_bleak/cmd.py
decora_bleak/const.py
decora_bleak/decora_bleak.py
decora_bleak/exceptions.py
decora_bleak/models.py
decora_bleak-0.2.2.dist-info/LICENSE
decora_bleak-0.2.2.dist-info/METADATA
decora_bleak-0.2.2.dist-info/WHEEL
decora_bleak-0.2.2.dist-info/entry_points.txt
decora_bleak-0.2.2.dist-info/top_level.txt
decora_bleak-0.2.2.dist-info/RECORD
