Metadata-Version: 2.1
Name: decora-bleak
Version: 0.2.2
Summary: A package for interacting with Decora switches and dimmers over BLE
Author-email: Colin Campbell <colin.campbell@gmail.com>
Classifier: Development Status :: 3 - Alpha
Classifier: Programming Language :: Python :: 3
Classifier: License :: OSI Approved :: MIT License
Classifier: Operating System :: OS Independent
Requires-Python: >=3.7
License-File: LICENSE
Requires-Dist: bleak >=0.20.2
Requires-Dist: bleak-retry-connector >=3.0.0
Provides-Extra: dev
Requires-Dist: bumpver ; extra == 'dev'
Requires-Dist: isort ; extra == 'dev'
Requires-Dist: pip-tools ; extra == 'dev'
Requires-Dist: pytest ; extra == 'dev'
